Metadata-Version: 1.0
Name: blockrope
Version: 0.1.2
Summary: desc
Home-page: https://github.com/DanyZy/Blockrope
Author: Daniil Zgurovets
Author-email: daniilzgurovec@gmail.com
License: MIT
Platform: UNKNOWN
